msaris/__init__.py
msaris/clusterisation/__init__.py
msaris/clusterisation/clusterisation.py
msaris/formulas/__init__.py
msaris/formulas/monoisotopic_masses.py
msaris/formulas/optimisation.py
msaris/molecule/__init__.py
msaris/molecule/molecule.py
msaris/reader/__init__.py
msaris/reader/preprocessing.py
msaris/reader/reader.py
msaris/search/__init__.py
msaris/search/optimization_search.py
msaris/utils/__init__.py
msaris/utils/cluster_utils.py
msaris/utils/distributions_util.py
msaris/utils/intensities_util.py
msaris/utils/molecule_utils.py
msaris/utils/recognizing_utils.py
tests/__init__.py
tests/test_intensities_utils.py
tests/reader/__init__.py
tests/reader/test_preprocessing.py
tests/reader/test_reader.py
tests/test_data/__init__.py
tests/test_data/test_intensities_utils.py
tests/utils/__init__.py
tests/utils/test_intensities_utils.py
tests/utils/test_recognizing_utils.py
msaris-0.1.9.dist-info/LICENSE
msaris-0.1.9.dist-info/METADATA
msaris-0.1.9.dist-info/WHEEL
msaris-0.1.9.dist-info/top_level.txt
msaris-0.1.9.dist-info/RECORD
