Metadata-Version: 2.1
Name: msaris
Version: 0.1.9
Summary: Python package to identify isotope patterns and their formulas
Home-page: https://github.com/Borschevik/msaris
Author: Anton Bondarenko, Yulia Vlasova, Mikhail Polynski
License: MIT
Keywords: mass spectrometry,mass spec,isotopic,linear programming,isotope pattern,clusterization
Platform: UNKNOWN
Classifier: Programming Language :: Python :: 3
Classifier: License :: OSI Approved :: MIT License
Classifier: Intended Audience :: Science/Research
Classifier: Topic :: Scientific/Engineering :: Chemistry
Classifier: Topic :: Scientific/Engineering :: Information Analysis
Classifier: Operating System :: OS Independent
Classifier: Natural Language :: English
Requires-Python: >3.7
Requires-Dist: IsoSpecPy (>=2.1.1)
Requires-Dist: PuLP (>=2.4)
Requires-Dist: molmass (>=2020.6.10)
Requires-Dist: multiprocess (>=0.70.11.1)
Requires-Dist: numpy (>=1.19.5)
Requires-Dist: openms (>=3.6.1)
Requires-Dist: pandas (>=1.2.0)
Requires-Dist: pyopenms (>=2.6.0)
Requires-Dist: pytest (>=6.2.2)
Requires-Dist: scipy (>=1.6.0)
Requires-Dist: typer (>=0.3.2)
